MANIFEST.in
README.rst
requirements.txt
setup.py
resumeschema/__init__.py
resumeschema/schema.json
resumeschema.egg-info/PKG-INFO
resumeschema.egg-info/SOURCES.txt
resumeschema.egg-info/dependency_links.txt
resumeschema.egg-info/requires.txt
resumeschema.egg-info/top_level.txt
resumeschema/test/__init__.py
resumeschema/test/invalid_resume.json
resumeschema/test/valid_resume.json