Metadata-Version: 1.1
Name: resumeschema
Version: 1.0.0
Summary: JSON schema validator for the resume-schema (https://github.com/jsonresume/resume-schema) spec
Home-page: http://github.com/underdogio/resumeschema-python
Author: Brett Langdon
Author-email: me@brett.is
License: MIT
Platform: UNKNOWN
Classifier: Development Status :: 5 - Production/Stable
Classifier: Intended Audience :: Developers
Classifier: License :: OSI Approved :: MIT License
Classifier: Operating System :: OS Independent
Classifier: Programming Language :: Python
Classifier: Programming Language :: Python :: 2
Classifier: Programming Language :: Python :: 2.7
Classifier: Programming Language :: Python :: 3
Classifier: Programming Language :: Python :: 3.4
Classifier: Programming Language :: Python :: Implementation :: CPython
Classifier: Programming Language :: Python :: Implementation :: PyPy
